oriented_matroids/__init__.py
oriented_matroids/abstract_oriented_matroid.py
oriented_matroids/all.py
oriented_matroids/catalog.py
oriented_matroids/circuit_oriented_matroid.py
oriented_matroids/covector_oriented_matroid.py
oriented_matroids/oriented_matroid.py
oriented_matroids/oriented_matroids_catalog.py
oriented_matroids/real_hyperplane_arrangement_oriented_matroid.py
oriented_matroids/signed_subset_element.py
oriented_matroids/vector_oriented_matroid.py
oriented_matroids-0.2.dist-info/licenses/LICENSE
oriented_matroids-0.2.dist-info/METADATA
oriented_matroids-0.2.dist-info/WHEEL
oriented_matroids-0.2.dist-info/top_level.txt
oriented_matroids-0.2.dist-info/RECORD
