Metadata-Version: 2.4
Name: oriented_matroids
Version: 0.2
Summary: Oriented matroids for sagemath
Author-email: Aram Dermenjian <aram.dermenjian.math@gmail.com>
License:                     GNU GENERAL PUBLIC LICENSE
Project-URL: Homepage, https://github.com/thecaligarmo/oriented_matroids
Project-URL: Bug Tracker, https://github.com/thecaligarmo/oriented_matroids/issues
Keywords: SageMath packaging
Classifier: Development Status :: 4 - Beta
Classifier: Intended Audience :: Science/Research
Classifier: Topic :: Scientific/Engineering :: Mathematics
Classifier: License :: OSI Approved :: GNU General Public License v3 or later (GPLv3+)
Requires-Python: >=3.8
License-File: LICENSE
Requires-Dist: sage-package
Requires-Dist: sphinx
Dynamic: license-file
